{
  "best_cost": 991.6457621079837,
  "best_params": {
    "low": [
      0.34,
      0.027,
      -0.074
    ],
    "high": [
      0.291,
      0.006,
      -0.057
    ]
  },
  "all_results": [
    {
      "id": 9,
      "low_gains": [
        0.34,
        0.027,
        -0.074
      ],
      "high_gains": [
        0.291,
        0.006,
        -0.057
      ],
      "avg_total_cost": 991.6457621079837,
      "num_files": 5,
      "std_cost": 711.9428066024093,
      "min_cost": 194.07354219498674,
      "max_cost": 2312.8641303028376,
      "test_time": 1.6809139251708984
    },
    {
      "id": 0,
      "low_gains": [
        0.3,
        0.03,
        -0.1
      ],
      "high_gains": [
        0.2,
        0.01,
        -0.05
      ],
      "avg_total_cost": 1632.5423364839055,
      "num_files": 5,
      "std_cost": 1478.0635610895374,
      "min_cost": 428.535717579678,
      "max_cost": 4460.017282499302,
      "test_time": 1.878894567489624
    },
    {
      "id": 6,
      "low_gains": [
        0.4,
        0.04,
        -0.12
      ],
      "high_gains": [
        0.2,
        0.01,
        -0.05
      ],
      "avg_total_cost": 1725.14502646719,
      "num_files": 5,
      "std_cost": 1264.9169750471758,
      "min_cost": 428.535717579678,
      "max_cost": 3966.200624120994,
      "test_time": 1.6558613777160645
    },
    {
      "id": 2,
      "low_gains": [
        0.3,
        0.03,
        -0.1
      ],
      "high_gains": [
        0.3,
        0.015,
        -0.06
      ],
      "avg_total_cost": 1871.2440088785836,
      "num_files": 5,
      "std_cost": 1275.4247468922772,
      "min_cost": 767.6430438511652,
      "max_cost": 4334.538573475934,
      "test_time": 1.666168451309204
    },
    {
      "id": 8,
      "low_gains": [
        0.4,
        0.04,
        -0.12
      ],
      "high_gains": [
        0.3,
        0.015,
        -0.06
      ],
      "avg_total_cost": 1983.692166637415,
      "num_files": 5,
      "std_cost": 1226.6713615037247,
      "min_cost": 767.6430438511652,
      "max_cost": 4257.754669205991,
      "test_time": 1.6685099601745605
    },
    {
      "id": 5,
      "low_gains": [
        0.35,
        0.05,
        -0.15
      ],
      "high_gains": [
        0.3,
        0.015,
        -0.06
      ],
      "avg_total_cost": 2237.04034131272,
      "num_files": 5,
      "std_cost": 1409.2408849182973,
      "min_cost": 765.5428190693146,
      "max_cost": 4756.264952289825,
      "test_time": 1.6812927722930908
    },
    {
      "id": 3,
      "low_gains": [
        0.35,
        0.05,
        -0.15
      ],
      "high_gains": [
        0.2,
        0.01,
        -0.05
      ],
      "avg_total_cost": 2245.8419546874793,
      "num_files": 5,
      "std_cost": 1820.9452047790396,
      "min_cost": 428.535717579678,
      "max_cost": 5483.38810601829,
      "test_time": 1.685631275177002
    },
    {
      "id": 1,
      "low_gains": [
        0.3,
        0.03,
        -0.1
      ],
      "high_gains": [
        0.25,
        0.02,
        -0.08
      ],
      "avg_total_cost": 2779.322317107034,
      "num_files": 5,
      "std_cost": 887.373455531465,
      "min_cost": 2135.5116313281906,
      "max_cost": 4531.956528065719,
      "test_time": 1.656270980834961
    },
    {
      "id": 7,
      "low_gains": [
        0.4,
        0.04,
        -0.12
      ],
      "high_gains": [
        0.25,
        0.02,
        -0.08
      ],
      "avg_total_cost": 2884.0395639888256,
      "num_files": 5,
      "std_cost": 971.2015798228418,
      "min_cost": 2134.82052644954,
      "max_cost": 4798.430574517923,
      "test_time": 1.6601824760437012
    },
    {
      "id": 4,
      "low_gains": [
        0.35,
        0.05,
        -0.15
      ],
      "high_gains": [
        0.25,
        0.02,
        -0.08
      ],
      "avg_total_cost": 3250.2726651343073,
      "num_files": 5,
      "std_cost": 1328.7568208875243,
      "min_cost": 2134.9746363186214,
      "max_cost": 5849.741953623862,
      "test_time": 1.647477626800537
    }
  ],
  "tested": 10,
  "attempted": 10,
  "success_rate": 1.0
}